Metadata-Version: 1.1
Name: py-json-rpc
Version: 0.0.6
Summary: Decorator based toolkit to use JSONRPC easy like Flask. Asyncio supported.
Home-page: https://github.com/hachibeeDI/py-json-rpc
Author: OGURA_Daiki
Author-email: UNKNOWN
License: MIT
Keywords: json rpc,asyncio
Platform: UNKNOWN
Classifier: Development Status :: 4 - Beta
Classifier: License :: OSI Approved :: MIT License
Classifier: Intended Audience :: Developers
Classifier: Operating System :: OS Independent
Classifier: Programming Language :: Python
Classifier: Programming Language :: Python :: 3 :: Only
